mathTorch/__init__.py
mathTorch-0.0.8.dist-info/LICENSE
mathTorch-0.0.8.dist-info/METADATA
mathTorch-0.0.8.dist-info/WHEEL
mathTorch-0.0.8.dist-info/top_level.txt
mathTorch-0.0.8.dist-info/RECORD
