Metadata-Version: 2.1
Name: mathTorch
Version: 0.0.8
Summary: some research for the ones who love the see the deep ends
Home-page: https://github.com/erfanzar/
Author: erfan zare chavoshi
Author-email: Erfan zare Chavoshi  <erfanzare82@yahoo.com>
License: MIT
Project-URL: Homepage, https://github.com/erfanzar/mathTorch
Requires: numpy
Requires: numba
Requires: json5
Requires: PyYAML
Requires-Python: >=3.6
License-File: LICENSE
